nonebot_plugin_taygedo_helper/__init__.py
nonebot_plugin_taygedo_helper/calculate.py
nonebot_plugin_taygedo_helper/config.py
nonebot_plugin_taygedo_helper/db.py
nonebot_plugin_taygedo_helper/migrations/2b9e70172056_first_revision.py
nonebot_plugin_taygedo_helper/model.py
nonebot_plugin_taygedo_helper/taygedoapi.py
nonebot_plugin_taygedo_helper-0.3.0.dist-info/METADATA
nonebot_plugin_taygedo_helper-0.3.0.dist-info/WHEEL
nonebot_plugin_taygedo_helper-0.3.0.dist-info/licenses/LICENSE
nonebot_plugin_taygedo_helper-0.3.0.dist-info/RECORD
