Metadata-Version: 2.4
Name: nonebot-plugin-taygedo-helper
Version: 0.3.0
Summary: 
License: MIT
License-File: LICENSE
Author: Irelia
Author-email: 1074822720@qq.com
Requires-Python: >=3.10,<4.0
Classifier: License :: OSI Approved :: MIT License
Classifier: Programming Language :: Python :: 3
Classifier: Programming Language :: Python :: 3.10
Classifier: Programming Language :: Python :: 3.11
Classifier: Programming Language :: Python :: 3.12
Classifier: Programming Language :: Python :: 3.13
Classifier: Programming Language :: Python :: 3.14
Requires-Dist: httpx (>=0.28.1)
Requires-Dist: nonebot-adapter-onebot (>=2.4.6,<3.0.0)
Requires-Dist: nonebot-plugin-apscheduler (>=0.5.0,<0.6.0)
Requires-Dist: nonebot-plugin-orm (>=0.7.7,<0.8.0)
Requires-Dist: nonebot-plugin-send-anything-anywhere (>=0.7.1,<0.8.0)
Requires-Dist: nonebot2 (>=2.4.1,<3.0.0)
Requires-Dist: pycryptodome (>=3.22.0,<4.0.0)
Requires-Dist: sqlalchemy (>=2.0.40,<3.0.0)
